pyimport2pkg/__init__.py
pyimport2pkg/cli.py
pyimport2pkg/database.py
pyimport2pkg/exporter.py
pyimport2pkg/filter.py
pyimport2pkg/mapper.py
pyimport2pkg/models.py
pyimport2pkg/parser.py
pyimport2pkg/resolver.py
pyimport2pkg/scanner.py
pyimport2pkg/data/mapping.db
pyimport2pkg/mappings/__init__.py
pyimport2pkg/mappings/hardcoded.py
pyimport2pkg/mappings/namespace.py
pyimport2pkg-1.0.0.dist-info/METADATA
pyimport2pkg-1.0.0.dist-info/WHEEL
pyimport2pkg-1.0.0.dist-info/entry_points.txt
pyimport2pkg-1.0.0.dist-info/top_level.txt
pyimport2pkg-1.0.0.dist-info/RECORD
